odoo/addons/base_technical_user/README.rst
odoo/addons/base_technical_user/__init__.py
odoo/addons/base_technical_user/__manifest__.py
odoo/addons/base_technical_user/i18n/de.po
odoo/addons/base_technical_user/i18n/es.po
odoo/addons/base_technical_user/i18n/fr.po
odoo/addons/base_technical_user/i18n/hr.po
odoo/addons/base_technical_user/i18n/it.po
odoo/addons/base_technical_user/i18n/nl_NL.po
odoo/addons/base_technical_user/i18n/pt.po
odoo/addons/base_technical_user/models/__init__.py
odoo/addons/base_technical_user/models/res_company.py
odoo/addons/base_technical_user/views/res_company_view.xml
odoo11_addon_base_technical_user-11.0.1.0.0.dist-info/DESCRIPTION.rst
odoo11_addon_base_technical_user-11.0.1.0.0.dist-info/METADATA
odoo11_addon_base_technical_user-11.0.1.0.0.dist-info/RECORD
odoo11_addon_base_technical_user-11.0.1.0.0.dist-info/WHEEL
odoo11_addon_base_technical_user-11.0.1.0.0.dist-info/metadata.json
odoo11_addon_base_technical_user-11.0.1.0.0.dist-info/top_level.txt
